pythonansi/__init__.py
pythonansi/ansicolors/__init__.py
pythonansi/ansicolors/colors.py
pythonansi-1.0.2.dist-info/LICENSE
pythonansi-1.0.2.dist-info/METADATA
pythonansi-1.0.2.dist-info/WHEEL
pythonansi-1.0.2.dist-info/top_level.txt
pythonansi-1.0.2.dist-info/RECORD
