Metadata-Version: 2.1
Name: pythonansi
Version: 1.0.2
Summary: Renkli yazdırma
Home-page: https://github.com/aylak-github/PYTHON-ANSI
Author: BasicBots
Author-email: sxxx@gmail.com
Classifier: Programming Language :: Python :: 3
Classifier: License :: OSI Approved :: MIT License
Classifier: Operating System :: OS Independent
Requires-Python: >=3.5.5
License-File: LICENSE
